dbsemaphore/__init__.py
dbsemaphore/admin.py
dbsemaphore/apps.py
dbsemaphore/contextmanager.py
dbsemaphore/models.py
dbsemaphore/semaphore.py
dbsemaphore/tests.py
dbsemaphore/management/commands/dbsemaphore-test-acquire.py
dbsemaphore/migrations/0001_initial.py
dbsemaphore/migrations/__init__.py
django_dbsemaphore-0.1.2.dist-info/licenses/LICENSE.txt
django_dbsemaphore-0.1.2.dist-info/METADATA
django_dbsemaphore-0.1.2.dist-info/WHEEL
django_dbsemaphore-0.1.2.dist-info/top_level.txt
django_dbsemaphore-0.1.2.dist-info/zip-safe
django_dbsemaphore-0.1.2.dist-info/RECORD
