Metadata-Version: 2.4
Name: django-dbsemaphore
Version: 0.1.2
Summary: django-dbsemaphore — multi-ticket semaphores implemented on top of DB row locks
Home-page: https://sr.ht/~nullenenenen/django-dbsemaphore/
Author: nullenenenen
Author-email: nullenenenen@gavagai.eu
License: LGPL-3.0+
Project-URL: Documentation, https://git.sr.ht/~nullenenenen/django-dbsemaphore/tree/master/item/README.md
Project-URL: Source, https://git.sr.ht/~nullenenenen/django-dbsemaphore/
Keywords: Django semaphore
Classifier: Development Status :: 3 - Alpha
Classifier: Framework :: Django
Classifier: Intended Audience :: Developers
Classifier: License :: OSI Approved :: GNU Lesser General Public License v3 or later (LGPLv3+)
Classifier: Operating System :: OS Independent
Classifier: Topic :: Software Development
Classifier: Topic :: Database
Classifier: Programming Language :: Python :: 3
Requires-Python: >=3.8
License-File: LICENSE.txt
Requires-Dist: Django>=3.2.0
Dynamic: license-file
